{
  "name": "오하은",
  "dob": "920610-2968984",
  "date": "2025-10-27",
  "medication_A": "암로디핀 5mg",
  "medication_B": "메트포르민 500mg",
  "medication_C": "하이드로코르티손 10mg",
  "medication_D": "심바스타틴 20mg",
  "dosage": "하루 1회, 저녁 식후",
  "code_A": "N30",
  "code_B": "K52",
  "code_C": "L27",
  "code_D": "G43",
  "disease_name_A": "의료법인 정산의료재단\n 효성병원, 한방과",
  "disease_name_B": "충북대학교병원, 내과",
  "hospital": "충북대학교병원, 영상의학과",
  "period_A_1": "2정",
  "period_A_2": "1",
  "period_A_3": "7",
  "period_B_1": "5ml",
  "period_B_2": "3회",
  "period_B_3": "30일",
  "period_C_1": "1정",
  "period_C_2": "3회",
  "period_C_3": "30일",
  "period_D_1": "1정",
  "period_D_2": "1",
  "period_D_3": "30"
}