{
  "name": "강민서",
  "dob": "000228-4761034",
  "date": "2025-10-27",
  "medication_A": "아목시실린 500mg",
  "medication_B": "아스피린 100mg",
  "medication_C": "레보티록신 50mcg",
  "medication_D": "심바스타틴 20mg",
  "dosage": "하루 1회, 아침 식후",
  "code_A": "L25",
  "code_B": "N39",
  "code_C": "M16",
  "code_D": "R50",
  "disease_name_A": "충북대학교병원, 가정의학과",
  "disease_name_B": "의료법인 정산의료재단\n 효성병원, 일반외과",
  "hospital": "의료법인 힐링의료재단\n 옥천성모병원, 산부인과",
  "period_A_1": "2정",
  "period_A_2": "3회",
  "period_A_3": "14",
  "period_B_1": "5ml",
  "period_B_2": "1",
  "period_B_3": "14",
  "period_C_1": "5ml",
  "period_C_2": "1",
  "period_C_3": "14일",
  "period_D_1": "2정",
  "period_D_2": "2회",
  "period_D_3": "5일"
}