{
  "name": "박하윤",
  "dob": "900104-2365516",
  "date": "2025-10-27",
  "medication_A": "아스피린 100mg",
  "medication_B": "하이드로코르티손 10mg",
  "medication_C": "하이드로코르티손 10mg",
  "medication_D": "로사르탄 50mg",
  "dosage": "하루 1회, 저녁 식후",
  "code_A": "H52",
  "code_B": "H53",
  "code_C": "E03",
  "code_D": "J03",
  "disease_name_A": "의료법인한마음의\n료재단하나병원, 산부인과",
  "disease_name_B": "의료법인한마음의\n료재단하나병원, 정형외과",
  "hospital": "의료법인 송암의료재단 마이크로병원,\n 영상의학과",
  "period_A_1": "1정",
  "period_A_2": "1",
  "period_A_3": "5일",
  "period_B_1": "10ML",
  "period_B_2": "3회",
  "period_B_3": "5",
  "period_C_1": "1정",
  "period_C_2": "3",
  "period_C_3": "5",
  "period_D_1": "1정",
  "period_D_2": "1회",
  "period_D_3": "5일"
}