{
  "name": "李军 리쥔",
  "dob": "981209-8282564",
  "date": "2025-10-27",
  "medication_A": "나프록센정 250mg",
  "medication_B": "도파민패치",
  "medication_C": "판피린",
  "medication_D": "나조넥스스프레이 50mcg",
  "dosage": "하루 3회, 아침/점심/저녁",
  "code_A": "B97",
  "code_B": "L25",
  "code_C": "H53",
  "code_D": "N20",
  "disease_name_A": "청주의료원, 내과",
  "disease_name_B": "충북대학교병원, 가정의학과",
  "hospital": "의료법인 힐링의료재단\n 옥천성모병원, 일반외과",
  "period_A_1": "2정",
  "period_A_2": "3",
  "period_A_3": "30일",
  "period_B_1": "10ml",
  "period_B_2": "3회",
  "period_B_3": "7일",
  "period_C_1": "1정",
  "period_C_2": "2",
  "period_C_3": "5일",
  "period_D_1": "5ml",
  "period_D_2": "1",
  "period_D_3": "5"
}