{
  "name": "吴芳",
  "dob": "910328-6159473",
  "date": "2025-10-27",
  "medication_A": "덱사메타손주 5mg/mL",
  "medication_B": "프로게스테론캡슐 100mg",
  "medication_C": "클로트리마졸크림 1%",
  "medication_D": "삭센다펜주",
  "dosage": "하루 2회, 식전",
  "code_A": "M51",
  "code_B": "L23",
  "code_C": "F32",
  "code_D": "L20",
  "disease_name_A": "청주의료원, 재활의학과",
  "disease_name_B": "충북대학교병원, 신경과",
  "hospital": "의료법인 명지의료재단\n 명지병원, 응급의학과",
  "period_A_1": "1정",
  "period_A_2": "3",
  "period_A_3": "7",
  "period_B_1": "5ml",
  "period_B_2": "2",
  "period_B_3": "7일",
  "period_C_1": "5ml",
  "period_C_2": "3",
  "period_C_3": "5일",
  "period_D_1": "1정",
  "period_D_2": "1회",
  "period_D_3": "7일"
}