{
  "name": "이유진",
  "dob": "971004-1545895",
  "date": "2025-10-27",
  "medication_A": "티어스인점안액",
  "medication_B": "세레브렉스캡슐 200mg",
  "medication_C": "하이드로코르티손연고",
  "medication_D": "프레가발린정 75mg",
  "dosage": "하루 1회, 아침 식후",
  "code_A": "M79",
  "code_B": "J06",
  "code_C": "E66",
  "code_D": "F33",
  "disease_name_A": "청주의료원, 외과",
  "disease_name_B": "부산대학교병원, 외과",
  "hospital": "재단법인베스티안재단베스티안병원,\n 내과",
  "period_A_1": "2정",
  "period_A_2": "2회",
  "period_A_3": "30일",
  "period_B_1": "5ml",
  "period_B_2": "1",
  "period_B_3": "5일",
  "period_C_1": "2정",
  "period_C_2": "3회",
  "period_C_3": "7일",
  "period_D_1": "5ml",
  "period_D_2": "3",
  "period_D_3": "14일"
}